{
  "configurations": [
    {
      "name": "Быстрая проверка",
      "description": "Быстрая проверка синхронизации между двумя устройствами",
      "config": {
        "count": 10,
        "delay": 100000,
        "samples": 5,
        "devices": [0, 1],
        "debug": false
      }
    },
    {
      "name": "Детальный анализ",
      "description": "Подробный анализ с большим количеством измерений",
      "config": {
        "count": 100,
        "delay": 250000,
        "samples": 10,
        "devices": [0, 1, 2],
        "debug": false
      }
    },
    {
      "name": "Непрерывный мониторинг",
      "description": "Непрерывный мониторинг синхронизации",
      "config": {
        "count": 0,
        "delay": 500000,
        "samples": 15,
        "devices": [0, 1],
        "debug": false
      }
    },
    {
      "name": "Высокочастотные измерения",
      "description": "Высокочастотные измерения для точного анализа",
      "config": {
        "count": 50,
        "delay": 50000,
        "samples": 20,
        "devices": [0, 1],
        "debug": false
      }
    },
    {
      "name": "Многодevice сравнение",
      "description": "Сравнение всех доступных PTP устройств",
      "config": {
        "count": 25,
        "delay": 200000,
        "samples": 8,
        "devices": [0, 1, 2, 3],
        "debug": false
      }
    },
    {
      "name": "Отладочный режим",
      "description": "Конфигурация для отладки с подробным выводом",
      "config": {
        "count": 5,
        "delay": 1000000,
        "samples": 3,
        "devices": [0, 1],
        "debug": true
      }
    }
  ],
  "device_presets": [
    {
      "name": "Стандартная пара",
      "devices": [0, 1],
      "description": "Стандартное сравнение первых двух PTP устройств"
    },
    {
      "name": "Тройка устройств",
      "devices": [0, 1, 2],
      "description": "Сравнение трех PTP устройств"
    },
    {
      "name": "Все устройства",
      "devices": [0, 1, 2, 3, 4, 5, 6, 7],
      "description": "Сравнение всех доступных PTP устройств (до 8)"
    }
  ],
  "timing_presets": [
    {
      "name": "Быстро",
      "delay": 50000,
      "samples": 5,
      "description": "Быстрые измерения для предварительной проверки"
    },
    {
      "name": "Стандартно",
      "delay": 100000,
      "samples": 10,
      "description": "Стандартные настройки для обычного использования"
    },
    {
      "name": "Точно",
      "delay": 250000,
      "samples": 15,
      "description": "Точные измерения для детального анализа"
    },
    {
      "name": "Максимальная точность",
      "delay": 500000,
      "samples": 25,
      "description": "Максимальная точность для критических измерений"
    }
  ],
  "usage_tips": [
    "Используйте 'Быстрая проверка' для первоначальной диагностики",
    "Применяйте 'Детальный анализ' для глубокого исследования проблем",
    "Включите 'Непрерывный мониторинг' для долгосрочного наблюдения",
    "Используйте 'Высокочастотные измерения' для анализа джиттера",
    "Применяйте 'Отладочный режим' при возникновении проблем"
  ],
  "performance_notes": [
    "Меньше delay = больше нагрузка на систему",
    "Больше samples = точнее результаты, но медленнее измерения",
    "Больше devices = экспоненциально больше вычислений",
    "count = 0 означает бесконечные измерения",
    "Рекомендуется использовать не более 4 устройств одновременно"
  ]
}
